aurt/__init__.py
aurt/api.py
aurt/caching.py
aurt/calibration_aux.py
aurt/cli.py
aurt/data_processing.py
aurt/dynamics_aux.py
aurt/file_system.py
aurt/generalized_maxwell_slip.py
aurt/joint_dynamics.py
aurt/linear_system.py
aurt/messages.py
aurt/num_sym_layers.py
aurt/rigid_body_dynamics.py
aurt/robot_calibration.py
aurt/robot_data.py
aurt/robot_dynamics.py
aurt/signal_processing.py
aurt-0.0.4.dist-info/LICENSE.txt
aurt-0.0.4.dist-info/METADATA
aurt-0.0.4.dist-info/WHEEL
aurt-0.0.4.dist-info/entry_points.txt
aurt-0.0.4.dist-info/top_level.txt
aurt-0.0.4.dist-info/RECORD
