Metadata-Version: 2.1
Name: aurt
Version: 0.0.4
Summary: A robot dynamic parameters calibration toolbox.
Home-page: https://github.com/INTO-CPS-Association/aurt/
Author: Emil Madsen, Daniella Tola, Claudio Gomes
Author-email: ema@ece.au.dk
License: UNKNOWN
Platform: UNKNOWN
Classifier: Programming Language :: Python :: 3
Classifier: Operating System :: OS Independent
Requires-Python: >=3.8
License-File: LICENSE.txt
Requires-Dist: numpy (>=1)
Requires-Dist: sympy (>=1)
Requires-Dist: pandas (>=1)
Requires-Dist: scikit-learn (>=0.24)
Requires-Dist: CacheMan
Provides-Extra: vis
Requires-Dist: roboticstoolbox-python ; extra == 'vis'
Requires-Dist: matplotlib (>=1) ; extra == 'vis'
